{
  "status": 200,
  "sample": {
    "data": [
      {
        "close": "669.5999",
        "high": "669.5999",
        "low": "669.5601",
        "open": "669.5601",
        "start_time": "2025-10-03T23:58:00Z",
        "volume": 931,
        "market_time": "po",
        "total_volume": 70492555,
        "end_time": "2025-10-03T23:59:00Z"
      },
      {
        "close": "669.59",
        "high": "669.59",
        "low": "669.59",
        "open": "669.59",
        "start_time": "2025-10-03T23:56:00Z",
        "volume": 219,
        "market_time": "po",
        "total_volume": 70491624,
        "end_time": "2025-10-03T23:57:00Z"
      },
      {
        "close": "669.6",
        "high": "669.6",
        "low": "669.6",
        "open": "669.6",
        "start_time": "2025-10-03T23:55:00Z",
        "volume": 3583,
        "market_time": "po",
        "total_volume": 70491405,
        "end_time": "2025-10-03T23:56:00Z"
      },
      {
        "close": "669.43",
        "high": "669.43",
        "low": "669.43",
        "open": "669.43",
        "start_time": "2025-10-03T23:50:00Z",
        "volume": 147,
        "market_time": "po",
        "total_volume": 70487822,
        "end_time": "2025-10-03T23:51:00Z"
      },
      {
        "close": "669.42",
        "high": "669.42",
        "low": "669.42",
        "open": "669.42",
        "start_time": "2025-10-03T23:49:00Z",
        "volume": 278,
        "market_time": "po",
        "total_volume": 70487675,
        "end_time": "2025-10-03T23:50:00Z"
      }
    ]
  }
}